appdaemontestframework/__init__.py
appdaemontestframework/assert_that.py
appdaemontestframework/automation_fixture.py
appdaemontestframework/common.py
appdaemontestframework/given_that.py
appdaemontestframework/hass_mocks.py
appdaemontestframework/pytest_conftest.py
appdaemontestframework/time_travel.py
appdaemontestframework/appdaemon_mock/__init__.py
appdaemontestframework/appdaemon_mock/appdaemon.py
appdaemontestframework/appdaemon_mock/scheduler.py
appdaemontestframework-5.0.0.dist-info/METADATA
appdaemontestframework-5.0.0.dist-info/WHEEL
appdaemontestframework-5.0.0.dist-info/licenses/LICENSE
appdaemontestframework-5.0.0.dist-info/RECORD
