Metadata-Version: 2.4
Name: appdaemontestframework
Version: 5.0.0
Summary: Clean, human-readable tests for Appdaemon
Project-URL: Homepage, https://floriankempenich.github.io/Appdaemon-Test-Framework
Project-URL: Documentation, https://floriankempenich.github.io/Appdaemon-Test-Framework
Project-URL: Repository, https://github.com/FlorianKempenich/Appdaemon-Test-Framework
Project-URL: Issues, https://github.com/FlorianKempenich/Appdaemon-Test-Framework/issues
Author-email: Florian Kempenich <Flori@nKempenich.com>
License-Expression: MIT
License-File: LICENSE
Keywords: appdaemon,clean-code,home-automation,homeassistant,tdd,test
Classifier: Development Status :: 4 - Beta
Classifier: Environment :: Console
Classifier: Framework :: Pytest
Classifier: Intended Audience :: Developers
Classifier: License :: OSI Approved :: MIT License
Classifier: Programming Language :: Python :: 3
Classifier: Programming Language :: Python :: 3.10
Classifier: Programming Language :: Python :: 3.11
Classifier: Programming Language :: Python :: 3.12
Classifier: Topic :: Home Automation
Classifier: Topic :: Software Development :: Testing
Classifier: Topic :: Utilities
Requires-Python: >=3.10
Requires-Dist: appdaemon>=4.0.0
Requires-Dist: mock>=3.0.5
Requires-Dist: packaging>=20.0
Requires-Dist: setuptools>=75.3.2
Provides-Extra: dev
Requires-Dist: autopep8>=1.5.0; extra == 'dev'
Requires-Dist: coverage[toml]>=6.0; extra == 'dev'
Requires-Dist: pylint>=2.0.0; extra == 'dev'
Requires-Dist: pytest-asyncio>=0.20.0; extra == 'dev'
Requires-Dist: pytest>=6.0.0; extra == 'dev'
Provides-Extra: test
Requires-Dist: coverage[toml]>=6.0; extra == 'test'
Requires-Dist: pytest-asyncio>=0.20.0; extra == 'test'
Requires-Dist: pytest>=6.0.0; extra == 'test'
